ocx_schema_parser/__init__.py
ocx_schema_parser/check.py
ocx_schema_parser/config.py
ocx_schema_parser/data_classes.py
ocx_schema_parser/documentor.py
ocx_schema_parser/elements.py
ocx_schema_parser/errors.py
ocx_schema_parser/helpers.py
ocx_schema_parser/ocxdownloader/__init__.py
ocx_schema_parser/ocxdownloader/downloader.py
ocx_schema_parser/ocxparser.py
ocx_schema_parser/transformer.py
ocx_schema_parser/utils/__init__.py
ocx_schema_parser/utils/utilities.py
ocx_schema_parser/xelement.py
ocx_schema_parser/xparse.py
ocx_schema_parser-1.8.5.dist-info/LICENSE
ocx_schema_parser-1.8.5.dist-info/METADATA
ocx_schema_parser-1.8.5.dist-info/WHEEL
ocx_schema_parser-1.8.5.dist-info/RECORD
